{
  "location": "Winding Rivulet",
  "orders": [
    {
      "fish": "River mussel",
      "quantity": "1",
      "mass": "30 g",
      "price": "5.76"
    },
    {
      "fish": "Chinese Sleeper",
      "quantity": "2",
      "mass": "30 g",
      "price": "6.63"
    },
    {
      "fish": "Ruffe",
      "quantity": "5",
      "mass": "20 g",
      "price": "9.45"
    },
    {
      "fish": "Common Roach",
      "quantity": "4",
      "mass": "50 g",
      "price": "9.66"
    },
    {
      "fish": "Gudgeon",
      "quantity": "5",
      "mass": "15 g",
      "price": "17.49"
    },
    {
      "fish": "Perch",
      "quantity": "5",
      "mass": "199 g",
      "price": "20.22"
    },
    {
      "fish": "Common Carp",
      "quantity": "1",
      "mass": "3 kg",
      "price": "26.48"
    },
    {
      "fish": "Tench",
      "quantity": "1",
      "mass": "600 g",
      "price": "29.20"
    },
    {
      "fish": "White-eye Bream",
      "quantity": "1",
      "mass": "600 g",
      "price": "116.89"
    },
    {
      "fish": "Grass Carp",
      "quantity": "1",
      "mass": "40 kg",
      "price": "536.73"
    }
  ]
}